README.rst
setup.py
frequency_analysis/__init__.py
frequency_analysis/db_create.py
frequency_analysis/frequency.py
frequency_analysis/results.py
frequency_analysis.egg-info/PKG-INFO
frequency_analysis.egg-info/SOURCES.txt
frequency_analysis.egg-info/dependency_links.txt
frequency_analysis.egg-info/requires.txt
frequency_analysis.egg-info/top_level.txt