Metadata-Version: 2.1
Name: frequency-analysis
Version: 0.1.4.4
Summary: Symbol/symbol bigram/word/word bigram frequency analyzer with excel output.
Home-page: https://github.com/uqqu/frequency_analysis
Author: uqqu
Keywords: frequency analysis bigram linguistic cryptanalysis
Classifier: Programming Language :: Python :: 3.8
Classifier: Topic :: Text Processing :: Linguistic
